[{"leagueId":"fc3d2d40-2ed1-4394-81f4-1e528f53110e","queueType":"RANKED_SOLO_5x5","tier":"BRONZE","rank":"III","summonerId":"Q-m4eO2qaShwM7EsdYveHalIbj3M_D98d6pi9TVujS587sE","summonerName":"00개간지00","leaguePoints":43,"wins":3,"losses":8,"veteran":false,"inactive":false,"freshBlood":false,"hotStreak":false},{"leagueId":"9074beb8-2ff3-4ae5-9435-ead5516abc2a","queueType":"RANKED_SOLO_5x5","tier":"BRONZE","rank":"III","summonerId":"8_iPt5CqQeePc23alucsJwqDbEyRK_-oGvYO6NFC79dLNVs","summonerName":"inho012","leaguePoints":0,"wins":32,"losses":45,"veteran":false,"inactive":false,"freshBlood":false,"hotStreak":false},{"leagueId":"ab66769b-6637-4f66-9ec6-48341448b908","queueType":"RANKED_SOLO_5x5","tier":"BRONZE","rank":"III","summonerId":"AXw_Zporlmbe_9ZfAOjLhRU92cMnpNKtqm8NRTyyAm6TUL0","summonerName":"20171018전역","leaguePoints":100,"wins":11,"losses":15,"veteran":false,"inactive":false,"freshBlood":false,"hotStreak":false,"miniSeries":{"target":2,"wins":1,"losses":0,"progress":"WNN"}},{"leagueId":"9d475f1c-ecf8-4d46-9651-7a1251382b7f","queueType":"RANKED_SOLO_5x5","tier":"BRONZE","rank":"III","summonerId":"83TTamIFrs0AGu3_V67-vGInRz9wi6kbHmcvcDJMaG4udS4","summonerName":"몽블랑 노란드","leaguePoints":87,"wins":10,"losses":8,"veteran":false,"inactive":false,"freshBlood":false,"hotStreak":true},{"leagueId":"e781c1e9-de9c-43ba-aa9a-598300c03d51","queueType":"RANKED_SOLO_5x5","tier":"BRONZE","rank":"III","summonerId":"SDgibkZT48M6GfVgQv2eYwlQpJsDghsD-txYcvEyYR0zy7A","summonerName":"형부쫌만더","leaguePoints":0,"wins":3,"losses":14,"veteran":false,"inactive":false,"freshBlood":false,"hotStreak":false},{"leagueId":"c0735890-ce53-42fe-a9a2-8a4015090bfe","queueType":"RANKED_SOLO_5x5","tier":"BRONZE","rank":"III","summonerId":"-BnYtqIGSIfWTs1_cdZSUq0uPm40S6IdPsXV0JY4rRDZ5Bg","summonerName":"영 완","leaguePoints":75,"wins":8,"losses":8,"veteran":false,"inactive":false,"freshBlood":false,"hotStreak":false},{"leagueId":"8c7582f5-d492-4da7-950c-71cd726f8d57","queueType":"RANKED_SOLO_5x5","tier":"BRONZE","rank":"III","summonerId":"WT9bX_8_bmD9baLZFBWCdW3IKvu36EskzAHqskA_ir1NdJE","summonerName":"Alwsbt","leaguePoints":80,"wins":29,"losses":38,"veteran":false,"inactive":false,"freshBlood":false,"hotStreak":false},{"leagueId":"7ac1f401-bbac-4903-bb2a-134e1191fe93","queueType":"RANKED_SOLO_5x5","tier":"BRONZE","rank":"III","summonerId":"enzYBlh_umOZBXsaMtEWeKGWuUEKgkpw4TEA4CwYP-pCPAs","summonerName":"당 삼","leaguePoints":0,"wins":25,"losses":34,"veteran":false,"inactive":false,"freshBlood":false,"hotStreak":false},{"leagueId":"310ad545-2312-4ed5-8dc8-5cb4d7783b97","queueType":"RANKED_SOLO_5x5","tier":"BRONZE","rank":"III","summonerId":"wnCKISIJnQq2EGz8Uv_BZlJ7x2xIvVjAQ5sX03GEVfgDHMQ","summonerName":"GodIike","leaguePoints":65,"wins":8,"losses":2,"veteran":false,"inactive":false,"freshBlood":true,"hotStreak":true},{"leagueId":"e3499502-d827-476f-b49b-50a980cf6dcd","queueType":"RANKED_SOLO_5x5","tier":"BRONZE","rank":"III","summonerId":"o8nLzDKa5FqIm23Qt84o8pYqMk45cb0_VkmNidrGavlDY9E","summonerName":"Chungha Official","leaguePoints":0,"wins":31,"losses":57,"veteran":false,"inactive":false,"freshBlood":false,"hotStreak":false},{"leagueId":"132345a0-08dd-4c38-9295-86c4b9709727","queueType":"RANKED_SOLO_5x5","tier":"BRONZE","rank":"III","summonerId":"bIwrdg7v_i3tMmtNa03aXGwvhW9Cd3Q0JlkllvRePp-CaFc","summonerName":"이스뎃트루","leaguePoints":21,"wins":81,"losses":96,"veteran":false,"inactive":false,"freshBlood":false,"hotStreak":false},{"leagueId":"f3faa3e9-f2f1-4b38-b677-ada570b8f305","queueType":"RANKED_SOLO_5x5","tier":"BRONZE","rank":"III","summonerId":"UOn4cBjoM4oo8GQ9O8neMJeuWAZlwScYFwzVH1VvGFZbyzw","summonerName":"대구의무경찰","leaguePoints":55,"wins":35,"losses":28,"veteran":false,"inactive":false,"freshBlood":false,"hotStreak":false},{"leagueId":"e3a4fcf5-24e9-4321-909e-bfd552dd5b0f","queueType":"RANKED_SOLO_5x5","tier":"BRONZE","rank":"III","summonerId":"4N3_m3Kx0EBYNXJoL202tdOOW8A-K8A8A2IYW8i8UPnAnPY","summonerName":"니엄마팽이치기","leaguePoints":77,"wins":19,"losses":11,"veteran":false,"inactive":false,"freshBlood":false,"hotStreak":true},{"leagueId":"9bcbdcdf-8d91-483e-b589-8c2da16b6cc2","queueType":"RANKED_SOLO_5x5","tier":"BRONZE","rank":"III","summonerId":"wCqTwCMUONc6ynzxqGswxqAJVjPT-SHCpcxInt-xXsmwF0w","summonerName":"고자무륵","leaguePoints":22,"wins":1,"losses":12,"veteran":false,"inactive":false,"freshBlood":false,"hotStreak":false},{"leagueId":"2220bd49-bffc-4814-8f47-1bcab9615b8d","queueType":"RANKED_SOLO_5x5","tier":"BRONZE","rank":"III","summonerId":"WHWGrHIFeSWt3ZzfCnQc1qDCRScOUe8jZzuOHj75R52_oMY","summonerName":"쉬크망","leaguePoints":9,"wins":53,"losses":67,"veteran":false,"inactive":false,"freshBlood":false,"hotStreak":false},{"leagueId":"c0aff000-3cd5-47ef-9cf1-ff03d3416fae","queueType":"RANKED_SOLO_5x5","tier":"BRONZE","rank":"III","summonerId":"POsjLSXE0C_ZKjVT4sOAQhkTIFlf-VvoMUePgoqPMhyYZZ4","summonerName":"규발끄","leaguePoints":3,"wins":4,"losses":6,"veteran":false,"inactive":false,"freshBlood":true,"hotStreak":false},{"leagueId":"5b9cde3a-7221-4967-b36c-0fefdaf0baef","queueType":"RANKED_SOLO_5x5","tier":"BRONZE","rank":"III","summonerId":"thGwhod3yR9NVgcV1Mpx_aXHvNIGJ2caUaBiPUyNewphSD4","summonerName":"뭘바쓰레빠","leaguePoints":71,"wins":8,"losses":13,"veteran":false,"inactive":false,"freshBlood":false,"hotStreak":false},{"leagueId":"c14f451e-3459-4a95-b91d-78cf89ed8c13","queueType":"RANKED_SOLO_5x5","tier":"BRONZE","rank":"III","summonerId":"l25cWOEikp3iQj19ZEi0vOBnlToYmiGX5QCckCydr1UNF-k","summonerName":"미 췬","leaguePoints":9,"wins":78,"losses":93,"veteran":false,"inactive":false,"freshBlood":false,"hotStreak":false},{"leagueId":"745fd3f0-df0d-41bf-9a7c-feac2b0ebdb9","queueType":"RANKED_SOLO_5x5","tier":"BRONZE","rank":"III","summonerId":"mEUIFg54xHVE6vS6Q5e6SgetSXwBfwrCfSjCkJu3Z01iRPY","summonerName":"께르페디엠","leaguePoints":81,"wins":7,"losses":8,"veteran":false,"inactive":false,"freshBlood":false,"hotStreak":false},{"leagueId":"eeb1bf96-e577-4c5a-852d-20dff485c8f8","queueType":"RANKED_SOLO_5x5","tier":"BRONZE","rank":"III","summonerId":"Bula_Yi7ATLHnjpAgJEiqh-ZtFUXjph1iJwZ7gHz-B4ZIXE","summonerName":"한구데기 술","leaguePoints":51,"wins":10,"losses":21,"veteran":false,"inactive":false,"freshBlood":false,"hotStreak":false},{"leagueId":"c5c66363-78ca-4a3b-aa33-6d3316df712c","queueType":"RANKED_SOLO_5x5","tier":"BRONZE","rank":"III","summonerId":"X5LFimMvUUFZkXOgSyjsgTBkml1nDS14atPU7vaEEw3hAeE","summonerName":"현대중공업생산직","leaguePoints":57,"wins":34,"losses":48,"veteran":false,"inactive":false,"freshBlood":false,"hotStreak":false},{"leagueId":"f4d10169-4abd-4954-b51b-4c5516a76cb9","queueType":"RANKED_SOLO_5x5","tier":"BRONZE","rank":"III","summonerId":"v8PyGXM6IDYNKCVGWGbS7PfuJeq62baOAUa1nQgoqmpun4Y","summonerName":"고자의꿈","leaguePoints":28,"wins":19,"losses":26,"veteran":false,"inactive":false,"freshBlood":false,"hotStreak":false},{"leagueId":"3cbad91a-648a-4729-ac74-e805a944c712","queueType":"RANKED_SOLO_5x5","tier":"BRONZE","rank":"III","summonerId":"UH6PiavOvXX94C2dBoyXY6R9sJwxecHvovVwwGvuOwBlaLU","summonerName":"Revolution of kr","leaguePoints":59,"wins":89,"losses":82,"veteran":false,"inactive":false,"freshBlood":false,"hotStreak":false},{"leagueId":"7bf474ea-450e-4bba-8c9b-c4e5b5b6a43b","queueType":"RANKED_SOLO_5x5","tier":"BRONZE","rank":"III","summonerId":"uQ7oaSf-928fBRTG_7grfjM255by9Cg0d08rWFSgOsl0J0E","summonerName":"딕더스트레인지","leaguePoints":47,"wins":24,"losses":23,"veteran":false,"inactive":false,"freshBlood":false,"hotStreak":false},{"leagueId":"8112d8ce-ec1f-421a-9de5-c0cd3f079c19","queueType":"RANKED_SOLO_5x5","tier":"BRONZE","rank":"III","summonerId":"V1KEX0V6Fbgin0gotUVWGl0vJZ2pToBYFK_f1yygADhloeA","summonerName":"대구불임약품","leaguePoints":67,"wins":33,"losses":51,"veteran":false,"inactive":false,"freshBlood":false,"hotStreak":false},{"leagueId":"2d43cac6-2dec-45f1-9b81-3b2786111bb3","queueType":"RANKED_SOLO_5x5","tier":"BRONZE","rank":"III","summonerId":"6FXZKfrYQqTXlHe5n8c9jGMfZa0nI_h62OFvXNfK9eTlQzQ","summonerName":"장팡덕","leaguePoints":15,"wins":44,"losses":69,"veteran":false,"inactive":false,"freshBlood":false,"hotStreak":false},{"leagueId":"f3a4b4ea-2789-4764-a578-ccfe1e223a75","queueType":"RANKED_SOLO_5x5","tier":"BRONZE","rank":"III","summonerId":"vP3Zx0sv0iuFf_jV9jqeo-05x1mGJIc6gIIgHmi7jg-0UNs","summonerName":"FlyHighJoon","leaguePoints":100,"wins":34,"losses":37,"veteran":false,"inactive":false,"freshBlood":false,"hotStreak":true,"miniSeries":{"target":2,"wins":0,"losses":0,"progress":"NNN"}},{"leagueId":"f65c7cfb-de9d-4f4e-b325-579ef60c2176","queueType":"RANKED_SOLO_5x5","tier":"BRONZE","rank":"III","summonerId":"hGC9sSjUUYL_tsMR2mKV7RBTFsWGzzHJGfTMx22sNFqbhZM","summonerName":"발렌타인500년산","leaguePoints":72,"wins":13,"losses":36,"veteran":false,"inactive":false,"freshBlood":false,"hotStreak":false},{"leagueId":"23fcec3c-78cf-47e1-a9d6-73e0d273fa41","queueType":"RANKED_SOLO_5x5","tier":"BRONZE","rank":"III","summonerId":"XEUkJqnsrCHgi4pF1yKU4TdPFqtu2Q9zpV5iIIx16f0IUq8","summonerName":"이순신카이팅","leaguePoints":86,"wins":7,"losses":7,"veteran":false,"inactive":false,"freshBlood":false,"hotStreak":false},{"leagueId":"07625bd4-6919-47e9-8b78-9c9cdbf451fb","queueType":"RANKED_SOLO_5x5","tier":"BRONZE","rank":"III","summonerId":"Rkixmhy-qwLMwR9ZXU2e5i8IWUMJKi7FDu9MQQs_VWltvqY","summonerName":"내이름승혁","leaguePoints":77,"wins":13,"losses":10,"veteran":false,"inactive":false,"freshBlood":false,"hotStreak":false},{"leagueId":"8d05c8a5-68d7-47eb-85aa-fb30386a0510","queueType":"RANKED_SOLO_5x5","tier":"BRONZE","rank":"III","summonerId":"y8QS9ZG6-S01j7naGu-QrJCsEHUf3S2THJiEL2vu6EsQ7ds","summonerName":"치킨맛코오돔","leaguePoints":90,"wins":4,"losses":6,"veteran":false,"inactive":false,"freshBlood":false,"hotStreak":false},{"leagueId":"e5a25058-743a-486c-aacb-86deb51e93a7","queueType":"RANKED_SOLO_5x5","tier":"BRONZE","rank":"III","summonerId":"kwpUd1nHBTe_C-P3z6sO4bCeUvfgT1cV5VNOhC8Utpmrbr4","summonerName":"엔터키가어디있죠","leaguePoints":79,"wins":142,"losses":150,"veteran":false,"inactive":false,"freshBlood":false,"hotStreak":false},{"leagueId":"3cab229f-9506-43d5-867b-535449672157","queueType":"RANKED_SOLO_5x5","tier":"BRONZE","rank":"III","summonerId":"MrYbvA86-OZUU_D_wTCi4Y6L1kApBAVWp5AmpyFi7DXcaD0","summonerName":"2Jh","leaguePoints":37,"wins":11,"losses":23,"veteran":false,"inactive":false,"freshBlood":false,"hotStreak":false},{"leagueId":"5983a030-a8a3-4f9e-bccb-2b9c16fe55e7","queueType":"RANKED_SOLO_5x5","tier":"BRONZE","rank":"III","summonerId":"xI_LzuEhEMx_MFIx2tRxHUUwoI2wN5d2HZc4qBr16d1MLww","summonerName":"개념없는세상","leaguePoints":0,"wins":191,"losses":219,"veteran":false,"inactive":false,"freshBlood":false,"hotStreak":false},{"leagueId":"9d1eb276-725b-4217-8ac3-dc38ed77e1c5","queueType":"RANKED_SOLO_5x5","tier":"BRONZE","rank":"III","summonerId":"4wMVE0U3bs5nTFkXwMzVRo7kK-AQYvwYe3qwRAlCRiFrZZE","summonerName":"빡치면게임안해요","leaguePoints":28,"wins":40,"losses":58,"veteran":false,"inactive":false,"freshBlood":false,"hotStreak":false},{"leagueId":"145ed9a8-f078-4e90-ac89-c11100710e0e","queueType":"RANKED_SOLO_5x5","tier":"BRONZE","rank":"III","summonerId":"7lPCTkrf3nlEWMAcH1swE9MPAC-fTGWYraA3cGHP3AZoXjc","summonerName":"아실만한분","leaguePoints":2,"wins":2,"losses":9,"veteran":false,"inactive":false,"freshBlood":false,"hotStreak":false},{"leagueId":"7fd6df02-12c2-489e-a927-3b7373cf02e9","queueType":"RANKED_SOLO_5x5","tier":"BRONZE","rank":"III","summonerId":"1GbNqJrhzo2slsPHfjfGFM4DUceqpbK7wVk0DtZz4iy7-gM","summonerName":"임천국","leaguePoints":0,"wins":7,"losses":7,"veteran":false,"inactive":false,"freshBlood":false,"hotStreak":false},{"leagueId":"54b240b7-16ef-4f13-909a-84a3ed7cf57a","queueType":"RANKED_SOLO_5x5","tier":"BRONZE","rank":"III","summonerId":"zwpg2VdkIHcFBaHHs_YsTmTTblvUh2g8uFadfQMjwWpNRUQ","summonerName":"카페헤이즐넛","leaguePoints":74,"wins":17,"losses":22,"veteran":false,"inactive":false,"freshBlood":false,"hotStreak":false},{"leagueId":"505ba46b-1a0c-4753-8ed3-e555fde48002","queueType":"RANKED_SOLO_5x5","tier":"BRONZE","rank":"III","summonerId":"YHiSLCf08sq8w3Rn8923wRf0GFGLk2h_xZTbbQxV5M1QpqY","summonerName":"강민경팬티도둑","leaguePoints":59,"wins":45,"losses":30,"veteran":false,"inactive":false,"freshBlood":false,"hotStreak":true},{"leagueId":"0d83af81-c851-4c70-baca-7beff92f927d","queueType":"RANKED_SOLO_5x5","tier":"BRONZE","rank":"III","summonerId":"eGvq9C4A4dWME_dxC-fwrxDEp28-TFe1AUET2zC-LZ3C3oY","summonerName":"WanMumu","leaguePoints":66,"wins":44,"losses":48,"veteran":false,"inactive":false,"freshBlood":false,"hotStreak":false},{"leagueId":"e5f32f5e-7f50-485e-a1a3-0b75c293cf79","queueType":"RANKED_SOLO_5x5","tier":"BRONZE","rank":"III","summonerId":"qaarr6AzYO7JQcB_TS97XitPbjO2SnAkRSHVfdhj_-x3gn4","summonerName":"의정부 맥그리거","leaguePoints":0,"wins":23,"losses":23,"veteran":false,"inactive":false,"freshBlood":false,"hotStreak":false},{"leagueId":"2ca4a40d-2c1c-4530-8eed-92c1cc9e623c","queueType":"RANKED_SOLO_5x5","tier":"BRONZE","rank":"III","summonerId":"gaunQuzsU8CYJgB3iPPXSbIu1SokI8JFyMPrzzSNp55WHtA","summonerName":"glory sword","leaguePoints":9,"wins":6,"losses":12,"veteran":false,"inactive":false,"freshBlood":false,"hotStreak":false},{"leagueId":"1cfd8e0d-705b-4519-a251-bdf4711fbd1f","queueType":"RANKED_SOLO_5x5","tier":"BRONZE","rank":"III","summonerId":"pJR_6gZCC2VgFLiBf9Cu5ZN9szhf46aJhgowcO_WADSQEek","summonerName":"애들아 살살하자","leaguePoints":48,"wins":8,"losses":4,"veteran":false,"inactive":false,"freshBlood":false,"hotStreak":false},{"leagueId":"1a4b6d73-9702-4c3b-9d57-d2cd95103020","queueType":"RANKED_SOLO_5x5","tier":"BRONZE","rank":"III","summonerId":"_hOagwZ3VVu39tLhaB3FqhVFfZYyQBXqykbO0K7UgWdyUww","summonerName":"여러분화내지마요","leaguePoints":100,"wins":23,"losses":25,"veteran":false,"inactive":false,"freshBlood":false,"hotStreak":true,"miniSeries":{"target":2,"wins":1,"losses":0,"progress":"WNN"}},{"leagueId":"7a18f6e4-1de3-4374-9282-cfff16f07a93","queueType":"RANKED_SOLO_5x5","tier":"BRONZE","rank":"III","summonerId":"b1eS5jxpAAmrQKAYfNpLI3hDWZK5Cx4K9UXVBzQ-SFL5NrU","summonerName":"Red Velvet빨간맛","leaguePoints":9,"wins":48,"losses":60,"veteran":false,"inactive":false,"freshBlood":false,"hotStreak":false},{"leagueId":"ee775eff-263d-409a-a8c0-afaedeff50e4","queueType":"RANKED_SOLO_5x5","tier":"BRONZE","rank":"III","summonerId":"1L9Q6ueE38c20Anzuy3ISw0Li1k2wxaZrgMBAUaXQ_uZopM","summonerName":"나 믿고 원딜가","leaguePoints":57,"wins":3,"losses":8,"veteran":false,"inactive":false,"freshBlood":false,"hotStreak":false},{"leagueId":"443de6f5-9ba4-46c9-a93d-a889bee526d3","queueType":"RANKED_SOLO_5x5","tier":"BRONZE","rank":"III","summonerId":"UCvpw5j59AzOYDp71ds-MezpE5cw9i53Mq5_JsX4TuN-bvo","summonerName":"메론참외","leaguePoints":10,"wins":4,"losses":6,"veteran":false,"inactive":false,"freshBlood":true,"hotStreak":false},{"leagueId":"5908c6d5-bfb4-4870-98c3-4091d11d6fb6","queueType":"RANKED_SOLO_5x5","tier":"BRONZE","rank":"III","summonerId":"EGhRiX6E8TqPgKLYXab5x-lbvbwVPUmcHZim5ZPXYampYA4","summonerName":"여자감성","leaguePoints":90,"wins":18,"losses":15,"veteran":false,"inactive":false,"freshBlood":false,"hotStreak":false},{"leagueId":"a0bed35e-a4f8-4687-849a-a6431f4eade0","queueType":"RANKED_SOLO_5x5","tier":"BRONZE","rank":"III","summonerId":"0sSbCyDenPis0_X_3SEaY1owBKtgtB4DhtJ9mBb9kP9qgOg","summonerName":"용인송담법률과","leaguePoints":94,"wins":13,"losses":10,"veteran":false,"inactive":false,"freshBlood":false,"hotStreak":false},{"leagueId":"1b327db8-4f58-45e4-b3b3-35ec50a84c37","queueType":"RANKED_SOLO_5x5","tier":"BRONZE","rank":"III","summonerId":"Ap_fOsqhuZ876cbWrlXe_2-Ql0M16A7_UOMa4cXcvCV2658","summonerName":"상욱이와서02","leaguePoints":86,"wins":37,"losses":52,"veteran":false,"inactive":false,"freshBlood":false,"hotStreak":true},{"leagueId":"bd83619f-cf0c-4cda-82be-c1cf1d11ce26","queueType":"RANKED_SOLO_5x5","tier":"BRONZE","rank":"III","summonerId":"2M9GEUI5V4WGLNQ79Lh_lutzHcFEvO1wZo6ZXxTtBEb4hKw","summonerName":"앓콩닳콩","leaguePoints":72,"wins":21,"losses":19,"veteran":false,"inactive":false,"freshBlood":false,"hotStreak":false},{"leagueId":"cab13d17-c55e-4873-b168-f1c390b3f4e5","queueType":"RANKED_SOLO_5x5","tier":"BRONZE","rank":"III","summonerId":"OJ8lYxdb94-_03vB06OjDdY9hapWbc4_NRvtjcrNHzXfvBE","summonerName":"xiao jeang fa","leaguePoints":97,"wins":8,"losses":7,"veteran":false,"inactive":false,"freshBlood":false,"hotStreak":false},{"leagueId":"2b5ca7da-882d-4b52-b7da-f7ffd0ec7ec7","queueType":"RANKED_SOLO_5x5","tier":"BRONZE","rank":"III","summonerId":"e6tBmuURALI54UvHafA5kpUMHO6W1JYu7285o5Wsb1QduAk","summonerName":"Forfuna","leaguePoints":41,"wins":128,"losses":142,"veteran":false,"inactive":false,"freshBlood":false,"hotStreak":false},{"leagueId":"71827bd1-9f03-4165-b777-cbbc22b530c8","queueType":"RANKED_SOLO_5x5","tier":"BRONZE","rank":"III","summonerId":"Ft3cIB0jwp3rguYCtxcbZf-jLbNomYhjL4Y_5cc-LqIcx3A","summonerName":"월송리개구리","leaguePoints":0,"wins":4,"losses":6,"veteran":false,"inactive":false,"freshBlood":true,"hotStreak":true},{"leagueId":"0a6105b5-70fd-4e23-a432-42238fdb76fb","queueType":"RANKED_SOLO_5x5","tier":"BRONZE","rank":"III","summonerId":"83T8Y3_ApFafxOHtzHkmouoLrPvIHzHOwP2iJOKXMur26NQ","summonerName":"우대기대기","leaguePoints":100,"wins":12,"losses":20,"veteran":false,"inactive":false,"freshBlood":false,"hotStreak":false,"miniSeries":{"target":2,"wins":1,"losses":1,"progress":"WLN"}},{"leagueId":"7361f623-623a-4fdf-b2de-6007cef459c5","queueType":"RANKED_SOLO_5x5","tier":"BRONZE","rank":"III","summonerId":"12TojvvOm7oKVjNVvr-N6kJ8nakF2JfeUeLbOtkZ_7kybrM","summonerName":"제일쎈놈1","leaguePoints":90,"wins":7,"losses":11,"veteran":false,"inactive":false,"freshBlood":false,"hotStreak":false},{"leagueId":"2b97a71c-dc99-4337-9c70-8df3b76a55f9","queueType":"RANKED_SOLO_5x5","tier":"BRONZE","rank":"III","summonerId":"gh8LvYbJFFkoDv9oC8StiUI00uUTBVekblPoApCfo2Cc46g","summonerName":"군향개","leaguePoints":82,"wins":6,"losses":5,"veteran":false,"inactive":false,"freshBlood":true,"hotStreak":false},{"leagueId":"5da1dcb2-58da-4e23-871a-ba4c70e5606a","queueType":"RANKED_SOLO_5x5","tier":"BRONZE","rank":"III","summonerId":"LBU4C7bd4EaLyaKkjPCjqr_CovEAn9IF1O6bjuOVqiYS84I","summonerName":"NIKE MAX 1 ","leaguePoints":56,"wins":48,"losses":53,"veteran":false,"inactive":false,"freshBlood":false,"hotStreak":true},{"leagueId":"b8ae10c8-4fdc-4601-99cd-eea577cd6d9a","queueType":"RANKED_SOLO_5x5","tier":"BRONZE","rank":"III","summonerId":"fDLzvCJFPCuhC4mcH4ToP7-u3wAag1BQEIvJi3TN4LjsIBE","summonerName":"철원군 꿀감자","leaguePoints":73,"wins":16,"losses":15,"veteran":false,"inactive":false,"freshBlood":false,"hotStreak":false},{"leagueId":"5f58e792-b936-42a7-be25-e64fc588349c","queueType":"RANKED_SOLO_5x5","tier":"BRONZE","rank":"III","summonerId":"ip0ThzmtikoyvXJcmYKhi4SLf2QY-s5OvpP4hQFE0qfmjSQ","summonerName":"운동아이하니","leaguePoints":35,"wins":20,"losses":31,"veteran":false,"inactive":false,"freshBlood":false,"hotStreak":false},{"leagueId":"ba45e834-776f-4a64-8cbf-0db63182006d","queueType":"RANKED_SOLO_5x5","tier":"BRONZE","rank":"III","summonerId":"mfNBaYPTUXtw0iNObHO8smFdrTiL4OHOInBhovUFZ95vfMA","summonerName":"이기용이다","leaguePoints":6,"wins":2,"losses":8,"veteran":false,"inactive":false,"freshBlood":false,"hotStreak":false},{"leagueId":"e1505529-df78-46cb-b6fd-1659768077f8","queueType":"RANKED_SOLO_5x5","tier":"BRONZE","rank":"III","summonerId":"JAdZ0JcPup0Y7qnMFgzCZCieTEo7MZTauU4NnnK0xM2dWRg","summonerName":"앵마토","leaguePoints":0,"wins":15,"losses":20,"veteran":false,"inactive":false,"freshBlood":false,"hotStreak":false},{"leagueId":"42a2fab3-4afa-4563-acb7-2160a3382470","queueType":"RANKED_SOLO_5x5","tier":"BRONZE","rank":"III","summonerId":"6D8bzAZfF06EbX89Fq7co7ZAj98R3S2rUM6q9ETL1S0ppIo","summonerName":"배승현존잘","leaguePoints":97,"wins":60,"losses":40,"veteran":false,"inactive":false,"freshBlood":false,"hotStreak":true},{"leagueId":"eddf8346-2e12-4945-a0a8-f2e1b973ff89","queueType":"RANKED_SOLO_5x5","tier":"BRONZE","rank":"III","summonerId":"tjqaEMP3gORpkuQAfJEWTDhg4FBnH_nwVrHFNeIf0WmS0cQ","summonerName":"현범대","leaguePoints":49,"wins":8,"losses":32,"veteran":false,"inactive":false,"freshBlood":false,"hotStreak":false},{"leagueId":"904adccb-8679-480f-874a-cb184adbc785","queueType":"RANKED_SOLO_5x5","tier":"BRONZE","rank":"III","summonerId":"Pp5f9RNtBObcaUJy7z6ZOYJ4_3ftFqpv7TrRjw38Od4z3pA","summonerName":"티모티모티모El모","leaguePoints":4,"wins":2,"losses":9,"veteran":false,"inactive":false,"freshBlood":false,"hotStreak":false},{"leagueId":"e8734e54-40ec-4131-a016-3be5e52bc3fa","queueType":"RANKED_SOLO_5x5","tier":"BRONZE","rank":"III","summonerId":"3aUft5RwjQRlVwia4drx02qTbR_sNiDSo1TPxDuH4nO06rk","summonerName":"블라즈카트르","leaguePoints":62,"wins":4,"losses":9,"veteran":false,"inactive":false,"freshBlood":false,"hotStreak":false},{"leagueId":"82b7bd28-ad6b-46c9-aab3-2d241807cc98","queueType":"RANKED_SOLO_5x5","tier":"BRONZE","rank":"III","summonerId":"hNqf_r9X9glCYMmXuFlhwblCBl8lZdrK1wldKknQ8Agtu1g","summonerName":"망고맛고기","leaguePoints":37,"wins":101,"losses":88,"veteran":false,"inactive":false,"freshBlood":false,"hotStreak":false},{"leagueId":"5a93d045-caa0-4fed-b694-284db1d8d8a3","queueType":"RANKED_SOLO_5x5","tier":"BRONZE","rank":"III","summonerId":"b2Sq8gEHGnuyP-GlO8InEzpYEoXX9SoD4DyP9O5ySt2Cihw","summonerName":"정진보","leaguePoints":45,"wins":7,"losses":19,"veteran":false,"inactive":false,"freshBlood":false,"hotStreak":false},{"leagueId":"68e2b319-0bb9-4e24-b756-7789a9301dbd","queueType":"RANKED_SOLO_5x5","tier":"BRONZE","rank":"III","summonerId":"tg2AHKnNyQyp75-yoh-8NHazVSmuzGRTAkM_SLk7Go0dkK8","summonerName":"계말년","leaguePoints":0,"wins":45,"losses":65,"veteran":true,"inactive":false,"freshBlood":false,"hotStreak":false},{"leagueId":"5783074c-04af-41f4-a0f3-50f91258b2da","queueType":"RANKED_SOLO_5x5","tier":"BRONZE","rank":"III","summonerId":"e9fZmD5QkQ88gRnVQROlyTR8kpFNu1aOoQPSLmGYUQJfnCU","summonerName":"퓨마는귀여워","leaguePoints":18,"wins":28,"losses":35,"veteran":false,"inactive":false,"freshBlood":false,"hotStreak":false},{"leagueId":"52c3204d-3a3e-48b4-a976-3e63b615d7d4","queueType":"RANKED_SOLO_5x5","tier":"BRONZE","rank":"III","summonerId":"5qPB10UvBXbILUSPeVqN7khqdyyUJYM68PDbTJOhqvczL7M","summonerName":"예술간져","leaguePoints":72,"wins":22,"losses":17,"veteran":false,"inactive":false,"freshBlood":false,"hotStreak":false},{"leagueId":"f38890b1-0f2e-4337-88c6-abea8cb7e279","queueType":"RANKED_SOLO_5x5","tier":"BRONZE","rank":"III","summonerId":"0zsEgdOYp7KT_H0BbYhch7alT3TBf563ZOzNVy66Sadpca0","summonerName":"덤벼보셔용","leaguePoints":5,"wins":20,"losses":33,"veteran":false,"inactive":false,"freshBlood":false,"hotStreak":false},{"leagueId":"d643cbf6-b37f-43a6-8b19-a721dc33ce1f","queueType":"RANKED_SOLO_5x5","tier":"BRONZE","rank":"III","summonerId":"p8GxBS5L7-2jpegmBGjiCODnRH8Yr-dRja3Ax1MUWYFRtkg","summonerName":"미넵미넵","leaguePoints":100,"wins":5,"losses":7,"veteran":false,"inactive":false,"freshBlood":false,"hotStreak":false,"miniSeries":{"target":2,"wins":0,"losses":0,"progress":"NNN"}},{"leagueId":"f637c6a2-22b4-473f-a89e-95b839722a07","queueType":"RANKED_SOLO_5x5","tier":"BRONZE","rank":"III","summonerId":"0_kWg8XBd8ipa9e61AWGYnOdfWJzgue2ogyCxZhO1-hYzLo","summonerName":"쿵쾅언냐","leaguePoints":100,"wins":6,"losses":11,"veteran":false,"inactive":false,"freshBlood":false,"hotStreak":false,"miniSeries":{"target":2,"wins":0,"losses":0,"progress":"NNN"}},{"leagueId":"5ad5f13f-9303-4250-9155-47cef4d286ed","queueType":"RANKED_SOLO_5x5","tier":"BRONZE","rank":"III","summonerId":"qmBGZrCL_UD-BCJRyX0hbJJa3uZbD4ln6Y-LqfStjU2urYM","summonerName":"님들저만지키셈","leaguePoints":49,"wins":13,"losses":17,"veteran":false,"inactive":false,"freshBlood":false,"hotStreak":false},{"leagueId":"4aea967d-028e-4948-8b79-22646467abc8","queueType":"RANKED_SOLO_5x5","tier":"BRONZE","rank":"III","summonerId":"wKyAy38cr_UvQyZXJmHnT2hVteG9i38meqttgG8wBZTsELk","summonerName":"ppkkxxrr","leaguePoints":0,"wins":13,"losses":29,"veteran":false,"inactive":false,"freshBlood":false,"hotStreak":false},{"leagueId":"4a1d5e0e-6896-4562-9628-3785d2398b8b","queueType":"RANKED_SOLO_5x5","tier":"BRONZE","rank":"III","summonerId":"cAIrQqint9sx8_Mx7pQ3jDub45rcJTOx3Y89wF48YNGX4GU","summonerName":"33minutes","leaguePoints":89,"wins":42,"losses":46,"veteran":false,"inactive":false,"freshBlood":false,"hotStreak":false},{"leagueId":"9a846bcb-30a3-4dd2-81a1-5f538958b0b8","queueType":"RANKED_SOLO_5x5","tier":"BRONZE","rank":"III","summonerId":"lqWcEUOVxq0XJ3b0v_JrqewbAdNNtYY6ks9P0-SZOB2e9HU","summonerName":"Justice A","leaguePoints":0,"wins":2,"losses":18,"veteran":false,"inactive":false,"freshBlood":false,"hotStreak":false},{"leagueId":"074d002d-ff5c-4b3c-9012-57c3faeb7df2","queueType":"RANKED_SOLO_5x5","tier":"BRONZE","rank":"III","summonerId":"8WC7GNdgvXWL_FOpBStbSMs8BSgJRfHyfZxqCCLZM_rtgq0","summonerName":"콩에진","leaguePoints":38,"wins":4,"losses":11,"veteran":false,"inactive":false,"freshBlood":false,"hotStreak":false},{"leagueId":"ee74c0f8-6562-4260-940f-46c73aa28a1b","queueType":"RANKED_SOLO_5x5","tier":"BRONZE","rank":"III","summonerId":"cxp97j6AAudI_g-c2tljGLRt6zkEtsOIWfdbvh1-OK0WfUw","summonerName":"루이팬드래건","leaguePoints":67,"wins":221,"losses":208,"veteran":false,"inactive":false,"freshBlood":false,"hotStreak":false},{"leagueId":"0ffc7fd3-2e55-4a80-8221-bc9ef62381c1","queueType":"RANKED_SOLO_5x5","tier":"BRONZE","rank":"III","summonerId":"xmJppqURbtmzJH92__xITcsfjSnyx8BQMnytO9POutZXFz8","summonerName":"왕중왕중왕92","leaguePoints":0,"wins":14,"losses":13,"veteran":false,"inactive":false,"freshBlood":false,"hotStreak":false},{"leagueId":"6d8e8807-2f77-490a-b1b0-3fe55a26a21c","queueType":"RANKED_SOLO_5x5","tier":"BRONZE","rank":"III","summonerId":"Ud3_ZGUpdavzIfXIn_hnduQxyJcN8i2_kXgezxwkL2wjTJk","summonerName":"부캐라인연습용","leaguePoints":26,"wins":38,"losses":49,"veteran":false,"inactive":false,"freshBlood":false,"hotStreak":false},{"leagueId":"82c975fb-bf96-4a26-bd55-3a41f5191be1","queueType":"RANKED_SOLO_5x5","tier":"BRONZE","rank":"III","summonerId":"sDVCr-1DDeGc7NKcbsv8Gd8Xf2PDd8ypU2oZgDRhbsht1VE","summonerName":"판태라","leaguePoints":46,"wins":66,"losses":93,"veteran":false,"inactive":false,"freshBlood":false,"hotStreak":true},{"leagueId":"b47d8911-67db-41b8-a5fb-aa6e0e533939","queueType":"RANKED_SOLO_5x5","tier":"BRONZE","rank":"III","summonerId":"pL5xYJkPd8G-roja1STAnhqfiEW6sHFY3ZntPIe80fjvFFE","summonerName":"낭만귀객","leaguePoints":6,"wins":93,"losses":98,"veteran":false,"inactive":false,"freshBlood":false,"hotStreak":false},{"leagueId":"24a06184-d2c7-451c-8be3-2f24789a8199","queueType":"RANKED_SOLO_5x5","tier":"BRONZE","rank":"III","summonerId":"GufAMCTIguvC4uvCT-UFQ4aCgi6oP-gkoqnXCGOftMJk2NA","summonerName":"고추소주","leaguePoints":75,"wins":68,"losses":79,"veteran":false,"inactive":false,"freshBlood":false,"hotStreak":false},{"leagueId":"038698ab-f1a8-4761-b76f-b39b4b2a2fb9","queueType":"RANKED_SOLO_5x5","tier":"BRONZE","rank":"III","summonerId":"_wYVLjH-TUc0CUrdsjNIlUaIbJSwfE-BG-DuaFYxSvp5nUA","summonerName":"종털이","leaguePoints":100,"wins":16,"losses":11,"veteran":false,"inactive":false,"freshBlood":false,"hotStreak":true,"miniSeries":{"target":2,"wins":1,"losses":0,"progress":"WNN"}},{"leagueId":"935562ad-87a2-4caf-9c38-8e015c560dc6","queueType":"RANKED_SOLO_5x5","tier":"BRONZE","rank":"III","summonerId":"Wc-sRtr-pc9s8xNheYZ_-oaD1uWcwP1YZWQlB8xDpZfwEsw","summonerName":"chel시","leaguePoints":27,"wins":23,"losses":37,"veteran":false,"inactive":false,"freshBlood":false,"hotStreak":false},{"leagueId":"3b983621-2b05-475c-8364-7f0769957fb7","queueType":"RANKED_SOLO_5x5","tier":"BRONZE","rank":"III","summonerId":"ZsM1By-avV3TWrgenmFOtz4uSnzVJG5ByVBeegB2v-O70V8","summonerName":"흉삼이와재일이","leaguePoints":36,"wins":28,"losses":27,"veteran":false,"inactive":false,"freshBlood":false,"hotStreak":false},{"leagueId":"64f6dde4-c363-4113-a508-8bcd5c1d6d38","queueType":"RANKED_SOLO_5x5","tier":"BRONZE","rank":"III","summonerId":"4oEtVzfEAYwN9b3Gt8QIbSrwE2RdoDo89Mq1-vtDSdy8k5Y","summonerName":"구준핵","leaguePoints":24,"wins":10,"losses":11,"veteran":false,"inactive":false,"freshBlood":false,"hotStreak":false},{"leagueId":"31a25933-2c46-41ff-b201-f1243fcedbdf","queueType":"RANKED_SOLO_5x5","tier":"BRONZE","rank":"III","summonerId":"FsOgZ1p0BWDs-m7W1IUdJhKfunEOeh7hqjg0Grf7XCD-CRM","summonerName":"KINSHHA","leaguePoints":84,"wins":121,"losses":125,"veteran":false,"inactive":false,"freshBlood":false,"hotStreak":false},{"leagueId":"b5284f97-3c5f-4123-a078-281870e79946","queueType":"RANKED_SOLO_5x5","tier":"BRONZE","rank":"III","summonerId":"qnYIhu_tGFxk2De_3ljjS1nUjIFFBeDQ8FjppHUJ5Qt0xrU","summonerName":"땡중입니당","leaguePoints":79,"wins":11,"losses":11,"veteran":false,"inactive":false,"freshBlood":false,"hotStreak":false},{"leagueId":"fda92551-9d59-42cd-9d0a-a26886edd9dd","queueType":"RANKED_SOLO_5x5","tier":"BRONZE","rank":"III","summonerId":"AljopMxksD7aAOcjUCNGBlHe8L6ic6ujn2kglSpUXwfxdkQ","summonerName":"때낀도로","leaguePoints":48,"wins":36,"losses":46,"veteran":false,"inactive":false,"freshBlood":false,"hotStreak":false},{"leagueId":"d824d525-09f4-4b19-af3a-e22aaf455fe1","queueType":"RANKED_SOLO_5x5","tier":"BRONZE","rank":"III","summonerId":"BA8YkfRaizvdwicxJHI7PywI3sOPeI8DA31axgy7UOlN3zY","summonerName":"준이어킴","leaguePoints":39,"wins":9,"losses":8,"veteran":false,"inactive":false,"freshBlood":false,"hotStreak":false},{"leagueId":"a30f66ec-b52f-4b28-95ac-b04c945de5a3","queueType":"RANKED_SOLO_5x5","tier":"BRONZE","rank":"III","summonerId":"3M_ootMbkmcoV2a6YcC8F--IV_E1aZUZd_AXsoC-z_RQ3nc","summonerName":"유승환입니다","leaguePoints":0,"wins":18,"losses":18,"veteran":false,"inactive":false,"freshBlood":false,"hotStreak":true},{"leagueId":"9105a72f-faa6-4862-923f-1fbff0b66736","queueType":"RANKED_SOLO_5x5","tier":"BRONZE","rank":"III","summonerId":"zjnErK7nfDSNPNfURkQUk9u1PjoYM2p7uTNjYrcZQh5-EXc","summonerName":"딸피도둑놈","leaguePoints":36,"wins":11,"losses":10,"veteran":false,"inactive":false,"freshBlood":false,"hotStreak":false},{"leagueId":"91b2f6a0-26bc-4146-a7cd-f476c3fbddbf","queueType":"RANKED_SOLO_5x5","tier":"BRONZE","rank":"III","summonerId":"y4Cq0UWxtbaURVjywOCdLqFRJNwyRA7iz23eUjzCSLeWFLw","summonerName":"PirusAndCrips","leaguePoints":75,"wins":9,"losses":14,"veteran":false,"inactive":false,"freshBlood":false,"hotStreak":false},{"leagueId":"c8a1ea05-87c6-4138-ab1d-63e8c41c1886","queueType":"RANKED_SOLO_5x5","tier":"BRONZE","rank":"III","summonerId":"fO0RAZ79GfQufjun3E5S_ZKPnaY3cZmVkmeHGBVorcWaZNs","summonerName":"ctcrime","leaguePoints":24,"wins":6,"losses":11,"veteran":false,"inactive":false,"freshBlood":false,"hotStreak":false},{"leagueId":"1d8e7289-3e27-453b-ba00-aa8fbce8c97b","queueType":"RANKED_SOLO_5x5","tier":"BRONZE","rank":"III","summonerId":"Tdc8JnpvPJeS3-nhVimu0mxWHIJTdZxzcXVzLnO_nXGVaSs","summonerName":"얼어붙은발톱","leaguePoints":39,"wins":102,"losses":113,"veteran":false,"inactive":false,"freshBlood":false,"hotStreak":false},{"leagueId":"c4e07691-4625-412a-bc78-b4b9203e1ec3","queueType":"RANKED_SOLO_5x5","tier":"BRONZE","rank":"III","summonerId":"piAtIy6RNQ2OZgHB7yP9-0b7ajBu_CqIN6eD7YSghdFfPxs","summonerName":"I Do Not Forgive","leaguePoints":46,"wins":27,"losses":48,"veteran":false,"inactive":false,"freshBlood":false,"hotStreak":false},{"leagueId":"f8785893-a6c9-4bd8-b87d-95bc5c4b65e4","queueType":"RANKED_SOLO_5x5","tier":"BRONZE","rank":"III","summonerId":"WEu3STktjsuJ5Hpg0B2Hlj53XMnsJ6iFJ1U53JiFh-B0npY","summonerName":"Ophion","leaguePoints":51,"wins":3,"losses":7,"veteran":false,"inactive":false,"freshBlood":false,"hotStreak":false},{"leagueId":"07e5e767-a483-4b4d-9e66-0421a8e90488","queueType":"RANKED_SOLO_5x5","tier":"BRONZE","rank":"III","summonerId":"nXAxVNMHEJiOHMVKLHtjl2PQjlVLLjsKZIP8STDEOg8HZAM","summonerName":"원딜차이오지고요","leaguePoints":71,"wins":79,"losses":78,"veteran":false,"inactive":false,"freshBlood":false,"hotStreak":false},{"leagueId":"c3216588-8f52-47ad-b88e-63a64c99011c","queueType":"RANKED_SOLO_5x5","tier":"BRONZE","rank":"III","summonerId":"PhIV3dtT3m5eI23U21BZ6yB4SLEYabzs3W8Hwfe-rbuaonI","summonerName":"빵석형","leaguePoints":57,"wins":71,"losses":100,"veteran":false,"inactive":false,"freshBlood":false,"hotStreak":false},{"leagueId":"e39a9b4d-20b3-44eb-8046-ac41d76c74d4","queueType":"RANKED_SOLO_5x5","tier":"BRONZE","rank":"III","summonerId":"D1VDPyDlrJx_aJiEC4am73WQCc8xgUFTPx1OSIXm0b2X9YY","summonerName":"시흥노브레이끼","leaguePoints":22,"wins":28,"losses":24,"veteran":false,"inactive":false,"freshBlood":false,"hotStreak":false},{"leagueId":"089baff9-08c5-43ce-a7b7-657df9e96b0f","queueType":"RANKED_SOLO_5x5","tier":"BRONZE","rank":"III","summonerId":"vgyrGreOUIT2iKenxhk_n-JiSJ-vK8YlWpYhXSQOWKaSlag","summonerName":"인수공주","leaguePoints":4,"wins":19,"losses":30,"veteran":false,"inactive":false,"freshBlood":false,"hotStreak":false},{"leagueId":"980ed908-3842-4b8d-8e6e-00cd3b4f71f3","queueType":"RANKED_SOLO_5x5","tier":"BRONZE","rank":"III","summonerId":"x2svxUHbjSHK6LNtt5bjcY6uGimD6Op58Yfqvp0bIg8Hfv8","summonerName":"Wmy","leaguePoints":46,"wins":3,"losses":7,"veteran":false,"inactive":false,"freshBlood":false,"hotStreak":false},{"leagueId":"46c2ed1d-d7f6-4266-936f-010478ddf879","queueType":"RANKED_SOLO_5x5","tier":"BRONZE","rank":"III","summonerId":"XVFLkFevT_oXOHaKBKzGtauAVrKuXJxGmOqOAO1shlZgb1s","summonerName":"신부동 폭풍갈퀴","leaguePoints":84,"wins":35,"losses":38,"veteran":false,"inactive":false,"freshBlood":false,"hotStreak":false},{"leagueId":"eab1f6c0-7199-49bc-a069-9f5882644a67","queueType":"RANKED_SOLO_5x5","tier":"BRONZE","rank":"III","summonerId":"8Ond_vB0sMDvFX7UfUUQ4aBYsDscR4SNMZyoJWRkCBpaqNc","summonerName":"GOLAN2","leaguePoints":58,"wins":11,"losses":22,"veteran":false,"inactive":false,"freshBlood":false,"hotStreak":false},{"leagueId":"bf878aee-f77e-4d72-89a9-399e0b5ec0c5","queueType":"RANKED_SOLO_5x5","tier":"BRONZE","rank":"III","summonerId":"26svEKAdmErlUegMGhpQKBQrso_n7zC9ArmYr4SKv6-AlRk","summonerName":"Hekate달","leaguePoints":10,"wins":20,"losses":26,"veteran":false,"inactive":false,"freshBlood":false,"hotStreak":false},{"leagueId":"7e0f1931-28fc-4cb7-9f2d-b02774929bd3","queueType":"RANKED_SOLO_5x5","tier":"BRONZE","rank":"III","summonerId":"sPn2SQVrrZYXdEzLy4M2_s4wovQ7mJsYJHUgSwNw63IfA_Y","summonerName":"대지원망","leaguePoints":0,"wins":3,"losses":12,"veteran":false,"inactive":false,"freshBlood":false,"hotStreak":false},{"leagueId":"f25f63d7-2a97-497b-8621-d3398c741c05","queueType":"RANKED_SOLO_5x5","tier":"BRONZE","rank":"III","summonerId":"tMRQh0FkatGPfqutCb_-NUH56S04mz9G9tKv5h2eDyAXmak","summonerName":"DoArm","leaguePoints":100,"wins":31,"losses":24,"veteran":false,"inactive":false,"freshBlood":false,"hotStreak":true,"miniSeries":{"target":2,"wins":1,"losses":0,"progress":"WNN"}},{"leagueId":"02a01e27-1d76-4c72-9dab-3b1072992d3d","queueType":"RANKED_SOLO_5x5","tier":"BRONZE","rank":"III","summonerId":"QG-m0D8OMprjyCy-1XRMj6hCBzCKFHj1EKgWVVcvbQrVTsw","summonerName":"계정찾습니다","leaguePoints":24,"wins":7,"losses":3,"veteran":false,"inactive":false,"freshBlood":false,"hotStreak":false},{"leagueId":"c260c0ef-b824-4661-840c-e8beef0d02c4","queueType":"RANKED_SOLO_5x5","tier":"BRONZE","rank":"III","summonerId":"aTHlU4iyifmFmSRpuviZQIf9Q8azKPh6g3GU6vA9kSqaxBc","summonerName":"나는덕자로소다","leaguePoints":86,"wins":5,"losses":9,"veteran":false,"inactive":false,"freshBlood":false,"hotStreak":true},{"leagueId":"b87a2c0b-4612-4b83-bc2c-f0cf5179fbff","queueType":"RANKED_SOLO_5x5","tier":"BRONZE","rank":"III","summonerId":"NfuqYKisLvXucTkKyMc3j02VDEltW5sS2jc9w5eJPp_3ztM","summonerName":"로제드","leaguePoints":0,"wins":64,"losses":80,"veteran":false,"inactive":false,"freshBlood":false,"hotStreak":false},{"leagueId":"2d7ac2c0-5ab3-4bb0-a1ef-dabe25e417bc","queueType":"RANKED_SOLO_5x5","tier":"BRONZE","rank":"III","summonerId":"AxpKBVeCM_OtmLRKL9TvJwBTbcR0Upfnd94ABsWHi9-KjhQ","summonerName":"상체103","leaguePoints":100,"wins":8,"losses":4,"veteran":false,"inactive":false,"freshBlood":false,"hotStreak":false,"miniSeries":{"target":2,"wins":0,"losses":0,"progress":"NNN"}},{"leagueId":"f4c32124-62f4-47a8-8bb6-286fccf6dcab","queueType":"RANKED_SOLO_5x5","tier":"BRONZE","rank":"III","summonerId":"mMSdorlQhiPcbwMVp2HPSn56prrMSukih7sYTBGmR1hix0w","summonerName":"꽃명그","leaguePoints":49,"wins":4,"losses":11,"veteran":false,"inactive":false,"freshBlood":false,"hotStreak":false},{"leagueId":"b60a7a9d-3a22-4959-a660-4d941d33c775","queueType":"RANKED_SOLO_5x5","tier":"BRONZE","rank":"III","summonerId":"l0xACnASY0g7hafzqCvt06ELb3IOBqNg37a_Jy-pUGMs7jM","summonerName":"링껀이","leaguePoints":54,"wins":60,"losses":70,"veteran":false,"inactive":false,"freshBlood":false,"hotStreak":false},{"leagueId":"802c51b1-99bb-4ce3-8629-2aa44b35f816","queueType":"RANKED_SOLO_5x5","tier":"BRONZE","rank":"III","summonerId":"_WilpLq1NS7_Hqnivep_2ABWxmhFEcvS5Dv41wXsWGnWbmM","summonerName":"감 재 영","leaguePoints":77,"wins":7,"losses":6,"veteran":false,"inactive":false,"freshBlood":false,"hotStreak":false},{"leagueId":"eb918ee2-e157-4a3b-9ea3-4db180386189","queueType":"RANKED_SOLO_5x5","tier":"BRONZE","rank":"III","summonerId":"JX4m2Xuby40EW8UmTLbNSkFXIIrfdPop4khIiHq20gBuUjg","summonerName":"wellstone","leaguePoints":0,"wins":25,"losses":21,"veteran":false,"inactive":false,"freshBlood":false,"hotStreak":false},{"leagueId":"45384dd5-6b33-440b-b0dd-2673c458fafc","queueType":"RANKED_SOLO_5x5","tier":"BRONZE","rank":"III","summonerId":"4EDekSC5qQ09kOk9vY6lR0nKoddhnRl31UVezsfgWcTRWu0","summonerName":"밍쿤이","leaguePoints":36,"wins":13,"losses":8,"veteran":false,"inactive":false,"freshBlood":false,"hotStreak":false},{"leagueId":"2e0b0221-9d63-45d6-870c-0a86aecafd13","queueType":"RANKED_SOLO_5x5","tier":"BRONZE","rank":"III","summonerId":"QFGH9hX9lWSFuaxX-u_4noeMDRt5PDotF3QdseNMB90sx8o","summonerName":"Vladimir of Top","leaguePoints":5,"wins":4,"losses":6,"veteran":false,"inactive":false,"freshBlood":false,"hotStreak":false},{"leagueId":"837d1d73-10e3-4cf6-8470-cb66a24c4084","queueType":"RANKED_SOLO_5x5","tier":"BRONZE","rank":"III","summonerId":"jmKwNyB-h6MhrjlPn8dI6Tton2Ds4kn-hTijJv8tnVHxmQk","summonerName":"빙굴스런공익생활","leaguePoints":72,"wins":24,"losses":26,"veteran":false,"inactive":false,"freshBlood":false,"hotStreak":false},{"leagueId":"8ed28c99-d6de-4f9a-a5b2-3a55f28256ee","queueType":"RANKED_SOLO_5x5","tier":"BRONZE","rank":"III","summonerId":"vUsOOlM20rUA6ny9qsZ_2qlNFN8r8azSVisXMIjSdkkZnoM","summonerName":"꼬우면던져든가","leaguePoints":9,"wins":18,"losses":24,"veteran":false,"inactive":false,"freshBlood":false,"hotStreak":false},{"leagueId":"8987355e-5574-41cf-a0bc-76faac46b54d","queueType":"RANKED_SOLO_5x5","tier":"BRONZE","rank":"III","summonerId":"HKQ1OZt9iNuDFj5BOPPKwqYNY6bzoPpz924scdnIw2LhL9A","summonerName":"빠쟁흐규","leaguePoints":33,"wins":106,"losses":96,"veteran":false,"inactive":false,"freshBlood":false,"hotStreak":false},{"leagueId":"30719ce0-ec5b-43dc-9da0-10280a25fff2","queueType":"RANKED_SOLO_5x5","tier":"BRONZE","rank":"III","summonerId":"FLtPFwDJdK9age-H--EDrH_mDniABUj3W2OwE8YKxImXMIU","summonerName":"오바쌍","leaguePoints":60,"wins":26,"losses":35,"veteran":false,"inactive":false,"freshBlood":false,"hotStreak":false},{"leagueId":"4ca64ea6-a30e-4702-90b4-b8f901976fd4","queueType":"RANKED_SOLO_5x5","tier":"BRONZE","rank":"III","summonerId":"dTor0I2deG3VoyjjhqLx372WODLttMfkM0-2iFzBySpxZt0","summonerName":"20210508","leaguePoints":49,"wins":3,"losses":8,"veteran":false,"inactive":false,"freshBlood":false,"hotStreak":false},{"leagueId":"39a13016-8c8a-4978-9000-40b65539a3b5","queueType":"RANKED_SOLO_5x5","tier":"BRONZE","rank":"III","summonerId":"NW3EuSfXpYiuVRti9QTM5tPAP4msRxn3wu2aPDV3WpL77Lc","summonerName":"쌍검킬","leaguePoints":0,"wins":9,"losses":8,"veteran":false,"inactive":false,"freshBlood":false,"hotStreak":true},{"leagueId":"fdccab84-a862-4cbc-9300-bca74e35a8b8","queueType":"RANKED_SOLO_5x5","tier":"BRONZE","rank":"III","summonerId":"4VUwuhjWgOd-4xG48bZkOZ6hqL0hbs-t6pZh8BoQ8MZH4rs","summonerName":"머억뻐","leaguePoints":38,"wins":164,"losses":203,"veteran":false,"inactive":false,"freshBlood":false,"hotStreak":false},{"leagueId":"677b4de8-ff74-4d34-a1fa-e46c706d98d5","queueType":"RANKED_SOLO_5x5","tier":"BRONZE","rank":"III","summonerId":"yrGCF_fulGQRbrAa_ete2_nwyOw43jOyQpG7UOuzXupjBTk","summonerName":"아니 태준아","leaguePoints":59,"wins":66,"losses":67,"veteran":false,"inactive":false,"freshBlood":false,"hotStreak":false},{"leagueId":"36e7c3d1-c46c-4d04-87b7-91e6cde296c3","queueType":"RANKED_SOLO_5x5","tier":"BRONZE","rank":"III","summonerId":"mpTffkdZaKLC-G6xLC8_sxuSl1rxxcD5ofPiDOCdI5z1idA","summonerName":"짱귀요미행이","leaguePoints":50,"wins":19,"losses":29,"veteran":false,"inactive":false,"freshBlood":false,"hotStreak":false},{"leagueId":"add4d344-aca3-4476-b7f4-93173cb17e68","queueType":"RANKED_SOLO_5x5","tier":"BRONZE","rank":"III","summonerId":"KeGFOUlJiFl9yC5KCluFAS-gHLXK5sIVEYXu8ULv5PzGQ54","summonerName":"쫌 기여워","leaguePoints":56,"wins":9,"losses":5,"veteran":false,"inactive":false,"freshBlood":false,"hotStreak":false},{"leagueId":"ea71acaf-a7ae-41a2-bc4b-e3d822aeafc8","queueType":"RANKED_SOLO_5x5","tier":"BRONZE","rank":"III","summonerId":"0QWDRuxFPLCvKVZAD2GHsSpOFP2m4eGGEKgqLpBhdvo5JrE","summonerName":"은도라지","leaguePoints":61,"wins":18,"losses":14,"veteran":false,"inactive":false,"freshBlood":false,"hotStreak":false},{"leagueId":"5736ad1d-de72-463b-9b8b-49d54fb9cfab","queueType":"RANKED_SOLO_5x5","tier":"BRONZE","rank":"III","summonerId":"N6aMFgzDKMC1jqlVvoGT1cT5Ya_yQrj1xuHHmB4eGxbhIzs","summonerName":"BACKTER","leaguePoints":0,"wins":22,"losses":23,"veteran":false,"inactive":false,"freshBlood":false,"hotStreak":false},{"leagueId":"e5d6d394-3558-4f93-be5d-c21d80b72375","queueType":"RANKED_SOLO_5x5","tier":"BRONZE","rank":"III","summonerId":"LJfLb-55LrbRXwYrNzfpl5sgzzLY1xDsuGFQvfW5UqXfLi0","summonerName":"Prince오브Dark","leaguePoints":100,"wins":13,"losses":12,"veteran":false,"inactive":false,"freshBlood":false,"hotStreak":false,"miniSeries":{"target":2,"wins":0,"losses":0,"progress":"NNN"}},{"leagueId":"f1f32a3a-ab23-4cfb-9378-7b27193a4114","queueType":"RANKED_SOLO_5x5","tier":"BRONZE","rank":"III","summonerId":"E49Bvile85Po_3ohHyKA75h68J2JODNJl3O-oJ9C-m_7mZo","summonerName":"햇앵갬롯뀨","leaguePoints":46,"wins":103,"losses":93,"veteran":false,"inactive":false,"freshBlood":false,"hotStreak":false},{"leagueId":"ad281b02-b0fd-4da8-a848-c6878b3c1f56","queueType":"RANKED_SOLO_5x5","tier":"BRONZE","rank":"III","summonerId":"SrVoqytOLPZWnEL90HNOHiTprDsSXH8kNDj1iPnJDo2PomU","summonerName":"탈론말고카타리나","leaguePoints":9,"wins":42,"losses":35,"veteran":false,"inactive":false,"freshBlood":false,"hotStreak":false},{"leagueId":"fa952558-f9a0-458b-8bc7-f610c63a6a8b","queueType":"RANKED_SOLO_5x5","tier":"BRONZE","rank":"III","summonerId":"oZWo7K4iGhzrGLB_-9C9oBimbi6TR9EansPiN7wgwFnuFFQ","summonerName":"종하니","leaguePoints":61,"wins":78,"losses":99,"veteran":false,"inactive":false,"freshBlood":false,"hotStreak":false},{"leagueId":"4e0c726a-917f-4fd5-9890-29d9023ee59b","queueType":"RANKED_SOLO_5x5","tier":"BRONZE","rank":"III","summonerId":"u3j9ME5uS-iibTyVZ1SdKe6Qf9I-Zr40ltm5GtxOkXgDIds","summonerName":"acacacacac","leaguePoints":67,"wins":17,"losses":9,"veteran":false,"inactive":false,"freshBlood":false,"hotStreak":false},{"leagueId":"569fd298-6403-4150-b2dc-4c9fc7d932d3","queueType":"RANKED_SOLO_5x5","tier":"BRONZE","rank":"III","summonerId":"v4hIN-WBqus-9-w4Zo7xb_WK-zUy51-Py8vlzxFgtcLYwFw","summonerName":"이름없는소환","leaguePoints":0,"wins":50,"losses":39,"veteran":false,"inactive":false,"freshBlood":false,"hotStreak":false},{"leagueId":"90c5d12c-f9ab-4396-b54f-29b95828d0dc","queueType":"RANKED_SOLO_5x5","tier":"BRONZE","rank":"III","summonerId":"9kl2DYsur9gK6Gq5WCtq-KvFZWJci9TDClnN3MgPPSUvtb8","summonerName":"뇨햐노매머어어","leaguePoints":65,"wins":82,"losses":73,"veteran":false,"inactive":false,"freshBlood":false,"hotStreak":false},{"leagueId":"4a6a1daa-9201-424b-bbb5-0b98c2bf580f","queueType":"RANKED_SOLO_5x5","tier":"BRONZE","rank":"III","summonerId":"nS_B-AoVEJAFDArtNMF796nrHy-lWx-L0rZv7IYP1cyx5s4","summonerName":"난 뺨맞은사람","leaguePoints":64,"wins":58,"losses":59,"veteran":false,"inactive":false,"freshBlood":false,"hotStreak":false},{"leagueId":"35256506-ef4a-4a8d-bebd-21cb48e65ed1","queueType":"RANKED_SOLO_5x5","tier":"BRONZE","rank":"III","summonerId":"joVvyh58YaJVLrRPxU6Ym_lSIKWoNfWZAhVCHIx-YAFqDVE","summonerName":"반송장기도둑","leaguePoints":70,"wins":6,"losses":5,"veteran":false,"inactive":false,"freshBlood":false,"hotStreak":false},{"leagueId":"61eb7ff9-d2e0-42c2-a130-80315cf09475","queueType":"RANKED_SOLO_5x5","tier":"BRONZE","rank":"III","summonerId":"moadaBSk5x1QSWddqsSCPON38gFUBIid1bp8MMzoIS8BpAA","summonerName":"경택이입니다만","leaguePoints":26,"wins":29,"losses":34,"veteran":false,"inactive":false,"freshBlood":false,"hotStreak":false},{"leagueId":"33e1fe74-3e71-4eb3-a4d1-ccf585f14415","queueType":"RANKED_SOLO_5x5","tier":"BRONZE","rank":"III","summonerId":"GScnEZZL97wOkruSuDGGWDQKx_kKZP1kH6k_TpLcTGZxrVg","summonerName":"몽둔이","leaguePoints":21,"wins":23,"losses":38,"veteran":false,"inactive":false,"freshBlood":false,"hotStreak":false},{"leagueId":"30d46bb2-992e-4084-943d-19a01592cd2e","queueType":"RANKED_SOLO_5x5","tier":"BRONZE","rank":"III","summonerId":"ldC0kxmoy-o5EofgD5-4SFFLwiw34930WM5lhsSHSjbUqk4","summonerName":"땅굴열차","leaguePoints":62,"wins":6,"losses":5,"veteran":false,"inactive":false,"freshBlood":false,"hotStreak":false},{"leagueId":"74456f5a-8ad7-4635-a2b3-5914f9b1304a","queueType":"RANKED_SOLO_5x5","tier":"BRONZE","rank":"III","summonerId":"W0fyTLNhxZPDSaCg8Dw4u6Zg6ku2GzWtLoWHn8g-V9lLiIg","summonerName":"HE썬","leaguePoints":62,"wins":47,"losses":62,"veteran":false,"inactive":false,"freshBlood":false,"hotStreak":false},{"leagueId":"206b06fb-7469-405d-a864-570dc87370b3","queueType":"RANKED_SOLO_5x5","tier":"BRONZE","rank":"III","summonerId":"At-wu83mqIOaJsWTpCyQ5Jp3XD-HQr1c_x6InyFs_oUBp4Q","summonerName":"우리정글언제오","leaguePoints":22,"wins":75,"losses":96,"veteran":false,"inactive":false,"freshBlood":false,"hotStreak":true},{"leagueId":"0869335d-428e-4c83-a374-c6c760ea2e2e","queueType":"RANKED_SOLO_5x5","tier":"BRONZE","rank":"III","summonerId":"5gQpsyYHnUacd-QL1UzR5HgTZdoIh5vYjv9GOrrWdUf4kT4","summonerName":"강미애","leaguePoints":46,"wins":12,"losses":14,"veteran":false,"inactive":false,"freshBlood":false,"hotStreak":true},{"leagueId":"0d9f576f-42c2-4a68-8f77-45623307806d","queueType":"RANKED_SOLO_5x5","tier":"BRONZE","rank":"III","summonerId":"f431tjj55gULteZTCR2HdVv4phaGi7djP7HW1K5jXhbr8Kc","summonerName":"리신master","leaguePoints":49,"wins":35,"losses":52,"veteran":false,"inactive":false,"freshBlood":false,"hotStreak":false},{"leagueId":"9b3fa190-9765-4fbd-b89e-36c7735f8518","queueType":"RANKED_SOLO_5x5","tier":"BRONZE","rank":"III","summonerId":"yYg-kQoaZju_odS3eYvyDHBh6ID6l69cP8_bMldVj5KSzdw","summonerName":"내크랩은살인이다","leaguePoints":65,"wins":46,"losses":31,"veteran":false,"inactive":false,"freshBlood":false,"hotStreak":false},{"leagueId":"aeb0997c-2833-4180-9283-d4d4413f180b","queueType":"RANKED_SOLO_5x5","tier":"BRONZE","rank":"III","summonerId":"zhKJyKdmYcIAbH8kLMytyAKSYfdYNrd9dWbRNYTxbFi2MRc","summonerName":"자기나싼다","leaguePoints":86,"wins":7,"losses":6,"veteran":false,"inactive":false,"freshBlood":false,"hotStreak":false},{"leagueId":"9d1ad1f4-f4df-478e-a425-cffdb478c4ea","queueType":"RANKED_SOLO_5x5","tier":"BRONZE","rank":"III","summonerId":"p9ns901koTOwVO2VNdpYVVH0eJ7jJwZtVAw-iw2c8CWvk_A","summonerName":"Tiicup","leaguePoints":95,"wins":13,"losses":16,"veteran":false,"inactive":false,"freshBlood":false,"hotStreak":false},{"leagueId":"fd28845e-b71e-4680-94a3-58ff1b029d6d","queueType":"RANKED_SOLO_5x5","tier":"BRONZE","rank":"III","summonerId":"qY2NlLaaiC31D9Rn2hjxdxiESkMo5vPtIsmOI-uNHWUAgfk","summonerName":"YugyoDragon","leaguePoints":69,"wins":12,"losses":20,"veteran":false,"inactive":false,"freshBlood":false,"hotStreak":false},{"leagueId":"9303c869-bbbb-464e-b246-a10a43f0c54e","queueType":"RANKED_SOLO_5x5","tier":"BRONZE","rank":"III","summonerId":"cdPqMO93ZuB6pJ0Ed16HQoQiQfRfGtCdOeqSW29tXPYqmAw","summonerName":"dadee","leaguePoints":48,"wins":8,"losses":2,"veteran":false,"inactive":false,"freshBlood":false,"hotStreak":true},{"leagueId":"887a350b-1412-4e59-ae66-f52801f08962","queueType":"RANKED_SOLO_5x5","tier":"BRONZE","rank":"III","summonerId":"bl7lhrb-lQgBI__s9is-xY0k-Nt2yYAfUoh8ejHsKWmWinY","summonerName":"Veuve Clicquot","leaguePoints":51,"wins":3,"losses":7,"veteran":false,"inactive":false,"freshBlood":false,"hotStreak":false},{"leagueId":"d21d68b6-d566-4e77-888c-cc580f8104d4","queueType":"RANKED_SOLO_5x5","tier":"BRONZE","rank":"III","summonerId":"brN9Alk7tLO5qO3oLJjtjI8WuSKe6e_FP_uHAFKDjEGpdgg","summonerName":"우왕 판테온떴당","leaguePoints":32,"wins":12,"losses":20,"veteran":false,"inactive":false,"freshBlood":false,"hotStreak":false},{"leagueId":"9b362f8d-86a4-4991-8cd6-53c000414977","queueType":"RANKED_SOLO_5x5","tier":"BRONZE","rank":"III","summonerId":"qX0x8KDZ4iSc4VHtdrWxkarSgfYqdj6UtjgNBZ9N03eZmO0","summonerName":"유진장칼국수","leaguePoints":0,"wins":31,"losses":25,"veteran":false,"inactive":false,"freshBlood":false,"hotStreak":false},{"leagueId":"0f2faa29-116c-4483-8d53-f0e6b23901b6","queueType":"RANKED_SOLO_5x5","tier":"BRONZE","rank":"III","summonerId":"BIoH0AGwkxOPxzzI_B4c7Zub9MT-LLimSVFfSLfYu3roOLE","summonerName":"강병주의 깨물근","leaguePoints":61,"wins":98,"losses":113,"veteran":false,"inactive":false,"freshBlood":false,"hotStreak":true},{"leagueId":"f81c9e4f-3ab9-4a45-b9d1-2bd7cf5d783d","queueType":"RANKED_SOLO_5x5","tier":"BRONZE","rank":"III","summonerId":"ukaKQ2-2BntDaOLQmXv1otqI6LJr0ohta0LJuM9wdWJC6cM","summonerName":"Slipa","leaguePoints":20,"wins":24,"losses":33,"veteran":false,"inactive":false,"freshBlood":false,"hotStreak":false},{"leagueId":"13b41f41-8c1a-4f23-8afb-80ea593b8094","queueType":"RANKED_SOLO_5x5","tier":"BRONZE","rank":"III","summonerId":"2t5X2LnCd0MHrUuan2JWdr1cJTsAVZ161nUnl6HZdO02BS4","summonerName":"누나먹고화이팅","leaguePoints":10,"wins":4,"losses":6,"veteran":false,"inactive":false,"freshBlood":false,"hotStreak":false},{"leagueId":"671e127e-4601-408e-8061-28041ae4050d","queueType":"RANKED_SOLO_5x5","tier":"BRONZE","rank":"III","summonerId":"aJG0oPx-HOZTKmt4umSMBXPSCa8cWI6cDnKZ8sFTpdsDMC0","summonerName":"골동품y","leaguePoints":12,"wins":11,"losses":16,"veteran":false,"inactive":false,"freshBlood":false,"hotStreak":false},{"leagueId":"c3975ac8-1262-4d53-8b09-579d81f0eb29","queueType":"RANKED_SOLO_5x5","tier":"BRONZE","rank":"III","summonerId":"Cl6QHK4KOCjVycydtWLKIrQZORDYtDvYhxqBO-IqbbCO83A","summonerName":"비똘끼","leaguePoints":63,"wins":4,"losses":8,"veteran":false,"inactive":false,"freshBlood":false,"hotStreak":false},{"leagueId":"7437633d-acf2-4a2b-b94d-0d2d4ab0c292","queueType":"RANKED_SOLO_5x5","tier":"BRONZE","rank":"III","summonerId":"jkvhi3qRHcIg2F-z9Y2Uhj94KORJmgvLxwsOHfGjCm9dEZ0","summonerName":"샴페인두방울","leaguePoints":98,"wins":69,"losses":93,"veteran":false,"inactive":false,"freshBlood":false,"hotStreak":false},{"leagueId":"28b3c6b2-cfdf-4034-bb68-daa0f2916596","queueType":"RANKED_SOLO_5x5","tier":"BRONZE","rank":"III","summonerId":"5WjMhnre8taEdvhrrKo7Osv0TEsND2pwQtEWZDywvn0iLm0","summonerName":"Taenon","leaguePoints":83,"wins":9,"losses":5,"veteran":false,"inactive":false,"freshBlood":false,"hotStreak":false},{"leagueId":"25f4f9dc-f1a7-4525-860f-604e2a1ffaac","queueType":"RANKED_SOLO_5x5","tier":"BRONZE","rank":"III","summonerId":"nfV9_iLaYwZxYE_qeeAeg32mNj83t7Iu_nGQDFeqZ8PhWBg","summonerName":"노지헤","leaguePoints":0,"wins":8,"losses":25,"veteran":false,"inactive":false,"freshBlood":false,"hotStreak":false},{"leagueId":"125e6b6c-39b1-4ebc-a807-dfe5f9f1f041","queueType":"RANKED_SOLO_5x5","tier":"BRONZE","rank":"III","summonerId":"n6cHrlmsy-0UW2Ngx3a5KYYpkJutYbWjIL6FxUxH1sMoo_Q","summonerName":"필리핀미녀들","leaguePoints":69,"wins":28,"losses":15,"veteran":false,"inactive":false,"freshBlood":false,"hotStreak":false},{"leagueId":"0aafe32d-ccb7-46d5-9712-3e6169fd5458","queueType":"RANKED_SOLO_5x5","tier":"BRONZE","rank":"III","summonerId":"IR32iQ8on8bmte2MMzCfdVGCHJPIFPH7Ysdlri4T7Hi_S5Q","summonerName":"산본파워","leaguePoints":7,"wins":5,"losses":13,"veteran":false,"inactive":false,"freshBlood":false,"hotStreak":false},{"leagueId":"3f5215f9-a109-4d0d-ad64-4915d4b1c4c8","queueType":"RANKED_SOLO_5x5","tier":"BRONZE","rank":"III","summonerId":"bDxfMTjLgukj71zv6VeqfspX63DGbGOG-phHcrFerVChjxA","summonerName":"마포구핵펀치","leaguePoints":100,"wins":33,"losses":34,"veteran":false,"inactive":false,"freshBlood":false,"hotStreak":false,"miniSeries":{"target":2,"wins":1,"losses":1,"progress":"WLN"}},{"leagueId":"904adccb-8679-480f-874a-cb184adbc785","queueType":"RANKED_SOLO_5x5","tier":"BRONZE","rank":"III","summonerId":"PGaR4HoDgPccXe8DJS1R4EaQoE_e7pvkX_R_2EUawN0WvYk","summonerName":"꼬 나","leaguePoints":95,"wins":10,"losses":3,"veteran":false,"inactive":false,"freshBlood":false,"hotStreak":true},{"leagueId":"2ec924dc-3159-43e1-9367-81bd30ce3a16","queueType":"RANKED_SOLO_5x5","tier":"BRONZE","rank":"III","summonerId":"HZC8kGb_TDRTmxKqWACD6fDvZwxiuh1XIAZt5LpRUCMscZw","summonerName":"무랑행님","leaguePoints":27,"wins":97,"losses":123,"veteran":false,"inactive":false,"freshBlood":false,"hotStreak":false},{"leagueId":"87ce669c-5c9d-4c40-a8e0-4fd7a97a43d5","queueType":"RANKED_SOLO_5x5","tier":"BRONZE","rank":"III","summonerId":"vtVx_wzAZ0xyLWOZasxEhLSuvSVKNkRbuQLnGaWSxUSmrCQ","summonerName":"성식 갓","leaguePoints":36,"wins":7,"losses":3,"veteran":false,"inactive":false,"freshBlood":false,"hotStreak":false},{"leagueId":"2a0bd15f-53da-4879-9123-935283026aef","queueType":"RANKED_SOLO_5x5","tier":"BRONZE","rank":"III","summonerId":"bBiT3gw0scH5TpSFYFN58eoKukSIeqpnxH2yM-3agkUJGZ4","summonerName":"미국급식충","leaguePoints":84,"wins":7,"losses":8,"veteran":false,"inactive":false,"freshBlood":false,"hotStreak":false},{"leagueId":"d4a777c2-3165-4fde-8b21-88adc32ff7c7","queueType":"RANKED_SOLO_5x5","tier":"BRONZE","rank":"III","summonerId":"jN4gpLN9a11NDMp7o_pKCJNRCU1u7puk8R8zxqAC2qreHW4","summonerName":"최인락","leaguePoints":36,"wins":7,"losses":14,"veteran":false,"inactive":false,"freshBlood":false,"hotStreak":false},{"leagueId":"236a11f8-477b-4158-b7a5-4ff05aabbfda","queueType":"RANKED_SOLO_5x5","tier":"BRONZE","rank":"III","summonerId":"3vsEYiz6bNff6yrFUu73-8ILQ8lAhPf8qF2lOBfDN-fuj0A","summonerName":"IlIlIlIIlllIll","leaguePoints":0,"wins":7,"losses":7,"veteran":false,"inactive":false,"freshBlood":false,"hotStreak":false},{"leagueId":"0a422103-48db-47d9-a6f1-dff627e1c856","queueType":"RANKED_SOLO_5x5","tier":"BRONZE","rank":"III","summonerId":"gzkhNyB6kRP069rwvyPH_9VbDX7J_D1o6gEdOjQaAweFUfU","summonerName":"김상우마스터","leaguePoints":0,"wins":29,"losses":23,"veteran":false,"inactive":false,"freshBlood":false,"hotStreak":false},{"leagueId":"1ab31fa8-f10c-41a0-8834-556dddffbcdc","queueType":"RANKED_SOLO_5x5","tier":"BRONZE","rank":"III","summonerId":"GaI53bWhgyILVVHWCc-DvrYEowTHPcWM9ofC_zTgTJTwrG8","summonerName":"이아준","leaguePoints":62,"wins":79,"losses":71,"veteran":false,"inactive":false,"freshBlood":false,"hotStreak":false},{"leagueId":"1637a9fd-e1e7-4074-ba52-ad220c100d91","queueType":"RANKED_SOLO_5x5","tier":"BRONZE","rank":"III","summonerId":"Ng4rMxeqUG9HBXeaQNdrM3asN9Km7CFgLAQ-3piST7JTAhM","summonerName":"창대와 아이들","leaguePoints":76,"wins":43,"losses":67,"veteran":false,"inactive":false,"freshBlood":false,"hotStreak":false},{"leagueId":"403910dd-6bb1-4581-96c5-aeda23953df0","queueType":"RANKED_SOLO_5x5","tier":"BRONZE","rank":"III","summonerId":"TB_SXryeEo1SnlkYDW18OquV3ypTxKlGTNF9mtAP5IwsV1M","summonerName":"M0VE 0N","leaguePoints":62,"wins":14,"losses":16,"veteran":false,"inactive":false,"freshBlood":false,"hotStreak":false},{"leagueId":"947a52c1-a3b5-4f80-9b2d-c51631554db5","queueType":"RANKED_SOLO_5x5","tier":"BRONZE","rank":"III","summonerId":"DcG3HQxjTQt5HfxStNGvettyPZrce31BLd4JNS9WE9h9cKw","summonerName":"IlllllolllllI","leaguePoints":54,"wins":7,"losses":16,"veteran":false,"inactive":false,"freshBlood":false,"hotStreak":false},{"leagueId":"55a5770f-5e91-4805-89ec-c0b1c126b8d7","queueType":"RANKED_SOLO_5x5","tier":"BRONZE","rank":"III","summonerId":"N0JG8fGYSx--eK0g_9jJtNcgv-TyIBu_lE5SAqVfxka4YGw","summonerName":"오르곤오른","leaguePoints":85,"wins":6,"losses":9,"veteran":false,"inactive":false,"freshBlood":false,"hotStreak":false},{"leagueId":"9c37d5b6-c911-4e97-bd45-de353dbbc0d5","queueType":"RANKED_SOLO_5x5","tier":"BRONZE","rank":"III","summonerId":"TJF7svyK-pYXUtbXkCesH9lPBYNlqE-fYu8KLe5VvWBErrQ","summonerName":"다윤띵","leaguePoints":86,"wins":57,"losses":74,"veteran":false,"inactive":false,"freshBlood":false,"hotStreak":false},{"leagueId":"2eeb736f-ee23-4e58-96c8-2b9da2767f20","queueType":"RANKED_SOLO_5x5","tier":"BRONZE","rank":"III","summonerId":"SDfO8_d33Cy9pcLWJpdzZk50VUddjfjNw8_AV1ekCJpJros","summonerName":"프후레쉬","leaguePoints":76,"wins":4,"losses":7,"veteran":false,"inactive":false,"freshBlood":false,"hotStreak":false},{"leagueId":"06210bcd-58ca-4ed0-9656-a7954dd5a237","queueType":"RANKED_SOLO_5x5","tier":"BRONZE","rank":"III","summonerId":"B5vQyUmTU5cN--CTp8ZbYkbzi3EpcQS1UMqWlSSgorPQrGo","summonerName":"임갱스터","leaguePoints":75,"wins":41,"losses":46,"veteran":false,"inactive":false,"freshBlood":false,"hotStreak":false},{"leagueId":"2681b8be-90c1-4e54-bf48-9c5ce58168f4","queueType":"RANKED_SOLO_5x5","tier":"BRONZE","rank":"III","summonerId":"UueLYtY2Nln-LOMyh-RU53dPbkwhopTnp-huCJddRTLflcY","summonerName":"암치원","leaguePoints":52,"wins":8,"losses":18,"veteran":false,"inactive":false,"freshBlood":false,"hotStreak":false},{"leagueId":"2e4d0286-70b2-4157-9987-4a06b859dc5e","queueType":"RANKED_SOLO_5x5","tier":"BRONZE","rank":"III","summonerId":"95kuNpjGETxqYtUaOO1yoBuGWrc0eobgR7KjXLQBi6Uvdy8","summonerName":"Cupid Vayne","leaguePoints":51,"wins":9,"losses":18,"veteran":false,"inactive":false,"freshBlood":false,"hotStreak":false},{"leagueId":"338d5866-748b-429d-81bf-14c57f3ba1de","queueType":"RANKED_SOLO_5x5","tier":"BRONZE","rank":"III","summonerId":"Ou5ywRZqPKTB4HzUn_lQxcYn1SeYa10Pqgp_Hf0OaOLM5J4","summonerName":"귀요미종현이","leaguePoints":34,"wins":25,"losses":24,"veteran":false,"inactive":false,"freshBlood":false,"hotStreak":false},{"leagueId":"08894b26-52e3-401b-954f-b290dd4e6498","queueType":"RANKED_SOLO_5x5","tier":"BRONZE","rank":"III","summonerId":"2OfoTX5ZtQ2CKlNcYbGc4_O9rVCBMsrSTRtB7bEczv3xxHA","summonerName":"큰날도","leaguePoints":46,"wins":56,"losses":73,"veteran":false,"inactive":false,"freshBlood":false,"hotStreak":false},{"leagueId":"5e35df2e-d3ad-48bd-99ca-488889f0a6ec","queueType":"RANKED_SOLO_5x5","tier":"BRONZE","rank":"III","summonerId":"92OyML-GYV00xj8dS4lcffAN6sMY2b9addbe_wGCmCnLMJk","summonerName":"너 박종의","leaguePoints":0,"wins":13,"losses":39,"veteran":false,"inactive":false,"freshBlood":false,"hotStreak":false},{"leagueId":"070e2c8b-fe65-4712-bcea-5b09af6c0464","queueType":"RANKED_SOLO_5x5","tier":"BRONZE","rank":"III","summonerId":"REwiC2Wjtz3a3dpg0LGziyn2PgnH7HmHoVmIuuXEqAmy2Zk","summonerName":"98년생배재현","leaguePoints":95,"wins":7,"losses":5,"veteran":false,"inactive":false,"freshBlood":false,"hotStreak":false},{"leagueId":"ec3f7a6c-66da-42fa-9461-3e06ba9b082f","queueType":"RANKED_SOLO_5x5","tier":"BRONZE","rank":"III","summonerId":"5N3dsa5cOTFdoiJBb3F-rAlLXF1SJLWi2lW0SRT32Ki9_Tw","summonerName":"우와 너희 어머","leaguePoints":83,"wins":9,"losses":13,"veteran":false,"inactive":false,"freshBlood":false,"hotStreak":false},{"leagueId":"35ef32c3-3377-4535-888b-19ea589c785e","queueType":"RANKED_SOLO_5x5","tier":"BRONZE","rank":"III","summonerId":"uvjqJXN5WEAyy1pCGVgdZlxpImCpD2MdpTlCIuiHNskFpp8","summonerName":"수석출신 F학점","leaguePoints":48,"wins":167,"losses":188,"veteran":false,"inactive":false,"freshBlood":false,"hotStreak":false},{"leagueId":"c5d8030f-1e6a-4fc8-bef3-56c73d32ac12","queueType":"RANKED_SOLO_5x5","tier":"BRONZE","rank":"III","summonerId":"Wtru0WvN1YMgYGkm0D9n3CJz4Hy408rwjBhXHZre_1SKbqI","summonerName":"Axis Lee","leaguePoints":18,"wins":32,"losses":43,"veteran":false,"inactive":false,"freshBlood":false,"hotStreak":false},{"leagueId":"505fafe2-fb53-4cb0-b337-b693abccb86e","queueType":"RANKED_SOLO_5x5","tier":"BRONZE","rank":"III","summonerId":"mjdrrEoodnCSiaLQIhJtTHsKMTToeviIj-86nzwXFcprJo0","summonerName":"CalipPenguin","leaguePoints":47,"wins":5,"losses":5,"veteran":false,"inactive":false,"freshBlood":false,"hotStreak":true},{"leagueId":"3f19c9d4-47f8-4278-a3b8-868eb867a86c","queueType":"RANKED_SOLO_5x5","tier":"BRONZE","rank":"III","summonerId":"WR8uDctmRTDB_8fNEFHvcYY7vjM2QP9powtaWSfJ2nYoEks","summonerName":"송와노","leaguePoints":74,"wins":10,"losses":11,"veteran":false,"inactive":false,"freshBlood":false,"hotStreak":false},{"leagueId":"9105e63d-7df4-4816-9bb5-cacb37407ef2","queueType":"RANKED_SOLO_5x5","tier":"BRONZE","rank":"III","summonerId":"-Bqv7zs4dqoKdVrWxMrH29nFBlzxEdIB8UkPb15bQ6lmjYc","summonerName":"심윤철","leaguePoints":21,"wins":10,"losses":22,"veteran":false,"inactive":false,"freshBlood":false,"hotStreak":false},{"leagueId":"089baff9-08c5-43ce-a7b7-657df9e96b0f","queueType":"RANKED_SOLO_5x5","tier":"BRONZE","rank":"III","summonerId":"JQ3C4Z8cBZxxxo4PQmE78fh40zm2_HQ_8ECVQtOYJDfZsYk","summonerName":"다엘 장","leaguePoints":0,"wins":90,"losses":99,"veteran":false,"inactive":false,"freshBlood":false,"hotStreak":false},{"leagueId":"20654d8c-3b42-44e1-91c3-f5c3ad2fb8df","queueType":"RANKED_SOLO_5x5","tier":"BRONZE","rank":"III","summonerId":"TyLqhSML4QEumTBMcYHzAbN7IDJYFkkCO7NF-WhDyQT0P_Q","summonerName":"구글영어사전","leaguePoints":54,"wins":48,"losses":57,"veteran":false,"inactive":false,"freshBlood":false,"hotStreak":false},{"leagueId":"8a2170bf-80dc-4b02-b645-67982b51d1f1","queueType":"RANKED_SOLO_5x5","tier":"BRONZE","rank":"III","summonerId":"2ci_8oKSrFu9Yz6oTtBWoWG8ge_kj4GctQAUnU5-CSPExcY","summonerName":"오준화 군대감","leaguePoints":0,"wins":9,"losses":13,"veteran":false,"inactive":false,"freshBlood":false,"hotStreak":false},{"leagueId":"d516c6c6-6bd5-42f8-a9c9-134dd02dd816","queueType":"RANKED_SOLO_5x5","tier":"BRONZE","rank":"III","summonerId":"7H-8-U6ZEnPXzh3p0WOTWrmbyPBdWtPP40UhLLMw8QopP0k","summonerName":"Fact폭행","leaguePoints":75,"wins":82,"losses":93,"veteran":false,"inactive":false,"freshBlood":false,"hotStreak":false},{"leagueId":"884130c4-f8a1-489b-ac88-cdb66f72469f","queueType":"RANKED_SOLO_5x5","tier":"BRONZE","rank":"III","summonerId":"0Qcb8ONfpVDgYnQ7JAUiCiIdehQ8f6d4-x1oq1VDTZ7rv4Y","summonerName":"산업기능요원임","leaguePoints":45,"wins":55,"losses":70,"veteran":false,"inactive":false,"freshBlood":false,"hotStreak":false},{"leagueId":"0225b09d-f9b8-49bd-ae65-5b3f039d4aed","queueType":"RANKED_SOLO_5x5","tier":"BRONZE","rank":"III","summonerId":"1qt1kTPCJMojYVOzKFSZV4n3Eo1-jbUejswScCz_lvIErAI","summonerName":"아잇푸아잉","leaguePoints":90,"wins":9,"losses":16,"veteran":false,"inactive":false,"freshBlood":false,"hotStreak":false},{"leagueId":"a9f7dce1-5eee-4893-9cc3-2cb02b4b1258","queueType":"RANKED_SOLO_5x5","tier":"BRONZE","rank":"III","summonerId":"4tieOPfgrQBzyMnKa6WmzM9th5J1q_-VK_SKoCCt91Jvx9A","summonerName":"하염없는 빛","leaguePoints":62,"wins":721,"losses":771,"veteran":false,"inactive":false,"freshBlood":false,"hotStreak":false},{"leagueId":"a3f4a60a-a78e-4680-9bd1-591b6fb39a86","queueType":"RANKED_SOLO_5x5","tier":"BRONZE","rank":"III","summonerId":"9RSTv2Jr_nywDMw0PEv3ah-bdz_301gzcBkeD2qNSWDWwAk","summonerName":"생오리는회오리","leaguePoints":52,"wins":39,"losses":44,"veteran":false,"inactive":false,"freshBlood":false,"hotStreak":false},{"leagueId":"b17504f6-25d3-4ca2-a367-dc9b447a004c","queueType":"RANKED_SOLO_5x5","tier":"BRONZE","rank":"III","summonerId":"cLE22FzBDb1xFm3mciThyjG8X7Z5t2ifg1sYx6HhUetEyJQ","summonerName":"o포도맛환타o","leaguePoints":61,"wins":14,"losses":14,"veteran":false,"inactive":false,"freshBlood":false,"hotStreak":false},{"leagueId":"941c0699-b20a-417b-b654-aa695bf873e8","queueType":"RANKED_SOLO_5x5","tier":"BRONZE","rank":"III","summonerId":"7qZCKb2jCb3mCxsRULDyuYvAC-4j1ZuRQDpL_6J_eUNnvEc","summonerName":"끕따기","leaguePoints":18,"wins":52,"losses":64,"veteran":false,"inactive":false,"freshBlood":false,"hotStreak":false},{"leagueId":"4bbf4e99-6cde-426e-a825-3c9bd54fa3c4","queueType":"RANKED_SOLO_5x5","tier":"BRONZE","rank":"III","summonerId":"mn7QAp0O5q14IeH2upkGuJ0pVijwcxlNoRYlhkSV2i0kWKE","summonerName":"zeratul27","leaguePoints":100,"wins":10,"losses":8,"veteran":false,"inactive":false,"freshBlood":false,"hotStreak":true,"miniSeries":{"target":2,"wins":1,"losses":0,"progress":"WNN"}}]
